pipekit_sdk/__init__.py
pipekit_sdk/_helpers.py
pipekit_sdk/models/__init__.py
pipekit_sdk/models/_config.py
pipekit_sdk/models/big.py
pipekit_sdk/models/inf.py
pipekit_sdk/models/intstr.py
pipekit_sdk/models/model.py
pipekit_sdk/models/resource.py
pipekit_sdk/models/v1.py
pipekit_sdk/models/v1alpha1.py
pipekit_sdk/service.py
pipekit_sdk-2.1.0.dist-info/LICENSE
pipekit_sdk-2.1.0.dist-info/METADATA
pipekit_sdk-2.1.0.dist-info/WHEEL
pipekit_sdk-2.1.0.dist-info/RECORD
