Metadata-Version: 2.1
Name: pipekit-sdk
Version: 2.1.0
Summary: Pipekit Python SDK
Home-page: https://pipekit.io
License: BSD-3-Clause
Keywords: pipekit,hera,argo,workflows,orchestration
Author: Pipekit
Author-email: ci@pipekit.io
Requires-Python: >=3.8,<4
Classifier: License :: OSI Approved :: BSD License
Classifier: Operating System :: OS Independent
Classifier: Programming Language :: Python :: 3
Classifier: Programming Language :: Python :: 3.8
Classifier: Programming Language :: Python :: 3.9
Classifier: Programming Language :: Python :: 3.10
Classifier: Programming Language :: Python :: 3.11
Classifier: Programming Language :: Python :: 3.12
Classifier: Programming Language :: Python :: 3.13
Requires-Dist: hera (>=5.5.2)
Requires-Dist: pydantic (<3)
Requires-Dist: pyjwt (>=2.9.0,<3.0.0)
Requires-Dist: responses (>=0.25.3,<0.26.0)
Project-URL: Documentation, https://docs.pipekit.io/
